{
  "id": "5900f46e1000cf542c50ff80",
  "title": "Problem 257: Angular Bisectors",
  "challengeType": 1,
  "forumTopicId": 301905,
  "dashedName": "problem-257-angular-bisectors",
  "challengeFiles": [
    {
      "head": "",
      "tail": "",
      "id": "",
      "editableRegionBoundaries": [],
      "history": [
        "script.js"
      ],
      "name": "script",
      "ext": "js",
      "path": "script.js",
      "fileKey": "scriptjs",
      "contents": "function angularBisectors() {\n\n  return true;\n}\n\nangularBisectors();",
      "error": null,
      "seed": "function angularBisectors() {\n\n  return true;\n}\n\nangularBisectors();"
    }
  ],
  "solutions": [
    [
      {
        "head": "",
        "tail": "",
        "id": "",
        "history": [
          "script.js"
        ],
        "name": "script",
        "ext": "js",
        "path": "script.js",
        "fileKey": "scriptjs",
        "contents": "// solution required",
        "error": null,
        "seed": "// solution required"
      }
    ]
  ],
  "assignments": [],
  "tests": [
    {
      "text": "<p><code>angularBisectors()</code> should return <code>139012411</code>.</p>",
      "testString": "assert.strictEqual(angularBisectors(), 139012411);"
    }
  ],
  "description": "<section id=\"description\">\n<p>Given is an integer sided triangle $ABC$ with sides $a ≤ b ≤ c$ ($AB = c$, $BC = a$ and $AC = b$).</p>\n<p>The angular bisectors of the triangle intersect the sides at points $E$, $F$ and $G$ (see picture below).</p>\n<img class=\"img-responsive center-block\" alt=\"triangle ABC, with angular bisectors intersecting sides at the points E, F and G\" src=\"https://cdn.freecodecamp.org/curriculum/project-euler/angular-bisectors.gif\" style=\"background-color: white; padding: 10px;\">\n<p>The segments $EF$, $EG$ and $FG$ partition the triangle $ABC$ into four smaller triangles: $AEG$, $BFE$, $CGF$ and $EFG$. It can be proven that for each of these four triangles the ratio $\\frac{\\text{area}(ABC)}{\\text{area}(\\text{subtriangle})}$ is rational. However, there exist triangles for which some or all of these ratios are integral.</p>\n<p>How many triangles $ABC$ with perimeter $≤ 100\\,000\\,000$ exist so that the ratio $\\frac{\\text{area}(ABC)}{\\text{area}(AEG)}$ is integral?</p>\n</section>",
  "translationPending": false,
  "block": "project-euler-problems-201-to-300",
  "hasEditableBoundaries": false,
  "order": 2,
  "superOrder": 16,
  "certification": "project-euler",
  "superBlock": "project-euler",
  "challengeOrder": 56,
  "required": [],
  "helpCategory": "Euler",
  "usesMultifileEditor": false,
  "disableLoopProtectTests": true,
  "disableLoopProtectPreview": false
}