{
  "id": "657e60811cb0f305e56bbe31",
  "title": "Task 106",
  "challengeType": 19,
  "dashedName": "task-106",
  "solutions": [],
  "question": {
    "text": "<p>Why does James say attending training is important?</p>",
    "answers": [
      {
        "answer": "<p>To meet new friends.</p>",
        "feedback": "<p>Training is more for learning than socializing.</p>"
      },
      {
        "answer": "<p>For fun and entertainment.</p>",
        "feedback": "<p>The purpose is educational, not just entertainment.</p>"
      },
      {
        "answer": "<p>To stay updated on regulations and best practices.</p>",
        "feedback": null
      },
      {
        "answer": "<p>To have longer breaks at work.</p>",
        "feedback": "<p>Training is for learning, not for extending breaks.</p>"
      }
    ],
    "solution": 3
  },
  "assignments": [],
  "scene": {
    "setup": {
      "background": "interview-room2.png",
      "characters": [
        {
          "character": "Linda",
          "position": {
            "x": 50,
            "y": 0,
            "z": 1.4
          },
          "opacity": 0
        },
        {
          "character": "James",
          "position": {
            "x": 50,
            "y": 15,
            "z": 1.2
          },
          "opacity": 0
        }
      ],
      "audio": {
        "filename": "2.1-4.mp3",
        "startTime": 1,
        "startTimestamp": 54.04,
        "finishTimestamp": 65.04
      }
    },
    "commands": [
      {
        "character": "Linda",
        "opacity": 1,
        "startTime": 0
      },
      {
        "character": "Linda",
        "startTime": 1,
        "finishTime": 4.66,
        "dialogue": {
          "text": "James, what about training? Do we have to attend training sessions regularly?",
          "align": "center"
        }
      },
      {
        "character": "Linda",
        "opacity": 0,
        "startTime": 4.7
      },
      {
        "character": "James",
        "opacity": 1,
        "startTime": 4.7
      },
      {
        "character": "James",
        "startTime": 5.06,
        "finishTime": 12,
        "dialogue": {
          "text": "Yes, you have to attend the training every year. It helps you stay updated on the latest regulations and best practices.",
          "align": "center"
        }
      },
      {
        "character": "James",
        "opacity": 0,
        "startTime": 12.5
      }
    ]
  },
  "tests": [],
  "description": "<section id=\"description\">\n<p>Attending training sessions, especially in a workplace, is important for many reasons. It helps employees learn new things, stay updated on rules or methods, and do their jobs better. For example: <code>Attending safety training helps workers prevent accidents.</code></p>\n</section>",
  "translationPending": false,
  "block": "learn-how-to-talk-about-a-typical-workday-and-tasks",
  "hasEditableBoundaries": false,
  "order": 3,
  "superOrder": 12,
  "certification": "a2-english-for-developers",
  "superBlock": "a2-english-for-developers",
  "challengeOrder": 109,
  "required": [],
  "helpCategory": "English",
  "usesMultifileEditor": false,
  "disableLoopProtectTests": false,
  "disableLoopProtectPreview": false
}