{
  "id": "5f3c866daec9a49519871816",
  "title": "Step 30",
  "challengeType": 0,
  "dashedName": "step-30",
  "challengeFiles": [
    {
      "head": "",
      "tail": "",
      "id": "",
      "editableRegionBoundaries": [
        15,
        18
      ],
      "history": [
        "index.html"
      ],
      "name": "index",
      "ext": "html",
      "path": "index.html",
      "fileKey": "indexhtml",
      "contents": "<!DOCTYPE html>\n<html lang=\"en\">\n  <head>\n    <meta charset=\"utf-8\" />\n    <meta name=\"viewport\" content=\"width=device-width, initial-scale=1.0\" />\n    <title>Cafe Menu</title>\n    <link href=\"styles.css\" rel=\"stylesheet\"/>\n  </head>\n  <body>\n    <div class=\"menu\">\n      <main>\n        <h1>CAMPER CAFE</h1>\n        <p>Est. 2020</p>\n        <section>\n          <h2>Coffee</h2>\n          <article>\n          </article>\n        </section>\n      </main>\n    </div>\n  </body>\n</html>",
      "error": null,
      "seed": "<!DOCTYPE html>\n<html lang=\"en\">\n  <head>\n    <meta charset=\"utf-8\" />\n    <meta name=\"viewport\" content=\"width=device-width, initial-scale=1.0\" />\n    <title>Cafe Menu</title>\n    <link href=\"styles.css\" rel=\"stylesheet\"/>\n  </head>\n  <body>\n    <div class=\"menu\">\n      <main>\n        <h1>CAMPER CAFE</h1>\n        <p>Est. 2020</p>\n        <section>\n          <h2>Coffee</h2>\n          <article>\n          </article>\n        </section>\n      </main>\n    </div>\n  </body>\n</html>"
    },
    {
      "head": "",
      "tail": "",
      "id": "",
      "editableRegionBoundaries": [],
      "history": [
        "styles.css"
      ],
      "name": "styles",
      "ext": "css",
      "path": "styles.css",
      "fileKey": "stylescss",
      "contents": "body {\n  background-image: url(https://cdn.freecodecamp.org/curriculum/css-cafe/beans.jpg);\n}\n\nh1, h2, p {\n  text-align: center;\n}\n\n.menu {\n  width: 80%;\n  background-color: burlywood;\n  margin-left: auto;\n  margin-right: auto;\n}",
      "error": null,
      "seed": "body {\n  background-image: url(https://cdn.freecodecamp.org/curriculum/css-cafe/beans.jpg);\n}\n\nh1, h2, p {\n  text-align: center;\n}\n\n.menu {\n  width: 80%;\n  background-color: burlywood;\n  margin-left: auto;\n  margin-right: auto;\n}"
    }
  ],
  "solutions": [],
  "assignments": [],
  "tests": [
    {
      "text": "<p>You should not change the existing <code>article</code> element.</p>",
      "testString": "assert($('article').length === 1);"
    },
    {
      "text": "<p>Your <code>article</code> element should have two <code>p</code> elements.</p>",
      "testString": "assert($('article').children('p').length === 2);"
    },
    {
      "text": "<p>Your first <code>p</code> element should have the text <code>French Vanilla</code>.</p>",
      "testString": "const firstP = $('article').children('p')[0];\nassert(firstP.innerText.match(/French Vanilla/i));"
    },
    {
      "text": "<p>Your second <code>p</code> element should have the text <code>3.00</code>.</p>",
      "testString": "const secondP = $('article').children('p')[1];\nassert(secondP.innerText.match(/3\\.00/i));"
    }
  ],
  "description": "<section id=\"description\">\n<p><code>article</code> elements commonly contain multiple elements that have related information. In this case, it will contain a coffee flavor and a price for that flavor. Nest two <code>p</code> elements inside your <code>article</code> element. The first one's text should be <code>French Vanilla</code>, and the second's text <code>3.00</code>.</p>\n</section>",
  "translationPending": false,
  "block": "learn-basic-css-by-building-a-cafe-menu",
  "hasEditableBoundaries": true,
  "order": 1,
  "superOrder": 0,
  "certification": "responsive-web-design",
  "superBlock": "2022/responsive-web-design",
  "challengeOrder": 29,
  "required": [],
  "helpCategory": "HTML-CSS",
  "usesMultifileEditor": true,
  "disableLoopProtectTests": false,
  "disableLoopProtectPreview": false
}