{
  "id": "5900f4301000cf542c50ff42",
  "title": "Problem 196: Prime triplets",
  "challengeType": 1,
  "forumTopicId": 301834,
  "dashedName": "problem-196-prime-triplets",
  "challengeFiles": [
    {
      "head": "",
      "tail": "",
      "id": "",
      "editableRegionBoundaries": [],
      "history": [
        "script.js"
      ],
      "name": "script",
      "ext": "js",
      "path": "script.js",
      "fileKey": "scriptjs",
      "contents": "function primeTriplets() {\n\n  return true;\n}\n\nprimeTriplets();",
      "error": null,
      "seed": "function primeTriplets() {\n\n  return true;\n}\n\nprimeTriplets();"
    }
  ],
  "solutions": [
    [
      {
        "head": "",
        "tail": "",
        "id": "",
        "history": [
          "script.js"
        ],
        "name": "script",
        "ext": "js",
        "path": "script.js",
        "fileKey": "scriptjs",
        "contents": "// solution required",
        "error": null,
        "seed": "// solution required"
      }
    ]
  ],
  "assignments": [],
  "tests": [
    {
      "text": "<p><code>primeTriplets()</code> should return <code>322303240771079940</code>.</p>",
      "testString": "assert.strictEqual(primeTriplets(), 322303240771079940);"
    }
  ],
  "description": "<section id=\"description\">\n<p>Build a triangle from all positive integers in the following way:</p>\n<p>$$\\begin{array}{rrr}\n&#x26;  1 \\\\\n&#x26;  \\color{red}{2} &#x26;  \\color{red}{3} \\\\\n&#x26;  4 &#x26; \\color{red}{5} &#x26;  6 \\\\\n&#x26;  \\color{red}{7} &#x26;  8 &#x26;  9 &#x26; 10 \\\\\n&#x26; \\color{red}{11} &#x26; 12 &#x26; \\color{red}{13} &#x26; 14 &#x26; 15  \\\\\n&#x26; 16 &#x26; \\color{red}{17} &#x26; 18 &#x26; \\color{red}{19} &#x26; 20 &#x26; 21 \\\\\n&#x26; 22 &#x26; \\color{red}{23} &#x26; 24 &#x26; 25 &#x26; 26 &#x26; 27 &#x26; 28 \\\\\n&#x26; \\color{red}{29} &#x26; 30 &#x26; \\color{red}{31} &#x26; 32 &#x26; 33 &#x26; 34 &#x26; 35 &#x26; 36 \\\\\n&#x26; \\color{red}{37} &#x26; 38 &#x26; 39 &#x26; 40 &#x26; \\color{red}{41} &#x26; 42 &#x26; \\color{red}{43} &#x26; 44 &#x26; 45 \\\\\n&#x26; 46 &#x26; \\color{red}{47} &#x26; 48 &#x26; 49 &#x26; 50 &#x26; 51 &#x26; 52 &#x26; \\color{red}{53} &#x26; 54 &#x26; 55 \\\\\n&#x26; 56 &#x26; 57 &#x26; 58 &#x26; \\color{red}{59} &#x26; 60 &#x26; \\color{red}{61} &#x26; 62 &#x26; 63 &#x26; 64 &#x26; 65 &#x26; 66 \\\\\n&#x26; \\cdots\n\\end{array}$$</p>\n<p>Each positive integer has up to eight neighbours in the triangle.</p>\n<p>A set of three primes is called a prime triplet if one of the three primes has the other two as neighbours in the triangle.</p>\n<p>For example, in the second row, the prime numbers 2 and 3 are elements of some prime triplet.</p>\n<p>If row 8 is considered, it contains two primes which are elements of some prime triplet, i.e. 29 and 31. If row 9 is considered, it contains only one prime which is an element of some prime triplet: 37.</p>\n<p>Define $S(n)$ as the sum of the primes in row $n$ which are elements of any prime triplet. Then $S(8) = 60$ and $S(9) = 37$.</p>\n<p>You are given that $S(10000) = 950007619$.</p>\n<p>Find $S(5678027) + S(7208785)$.</p>\n</section>",
  "translationPending": false,
  "block": "project-euler-problems-101-to-200",
  "hasEditableBoundaries": false,
  "order": 1,
  "superOrder": 16,
  "certification": "project-euler",
  "superBlock": "project-euler",
  "challengeOrder": 95,
  "required": [],
  "helpCategory": "Euler",
  "usesMultifileEditor": false,
  "disableLoopProtectTests": true,
  "disableLoopProtectPreview": false
}